{"effectiveDate": "2019-09-30", "edlMasterShareClassIdentifier": "09TB0317XXSCETF", "shareClassFullName": "Invesco Corporate Income Value ETF", "accountId": 38, "shareClassCurrency": "USD", "shareClassInceptionDate": "2018-07-25", "performanceInceptionDate": "2018-07-25", "shareClassShortName": "Invesco Corporate Income Value ETF", "shareClassStatus": "Open", "shareClassTerminationDate": "", "primaryShareClassIndicator": "True", "atlasAliasValueId": "1-1DD3PHY", "shareClassId": 34, "grossOrNetIndicator": "", "hedgedIndicator": "", "hedgedCurrencyCode": "", "isaEligible": "", "sippEligible": "", "ucitsCompliant": "", "dividendTreatment": "", "dividendSchedule": "", "ukReportingStatus": "", "registrationMatrix": [], "yields": {"secYield30Day": 0, "secUnsubsidizedYield30Day": 0}, "account": {"accountId": 38, "effectiveDate": "2019-09-30", "atlasPartyId": 30, "subType": "ACCT.FUND", "accountCode": "", "accountName": "Invesco Corporate Income Value ETF", "accountNumber": "IHYV", "accountCurrencyCode": "USD", "domicileCountryCode": "US", "accountFiscalYearEnd": "", "legalEntityIdentifier": "5493000INMFTM6FOHK38", "numberOfShareclasses": "", "performanceStartDate": "2018-07-25", "proxyVotingAuthority": "Sole", "accountStatus": "Open", "terminationDate": "", "accountLevelOfService": "ETF", "fundOfFunds": "False", "accountOpenDate": "2018-07-25", "edlMasterAccountIdentifier": "09TB0317XX", "accountingBasisName": "GAAP", "managementFeeType": "0.23%", "securityLendingAssetTypes": "No", "securityLendingParticipationFlag": "", "accountShortName": "", "accountTerminationReason": "", "taxId": "82-5368821", "fxRateSource": "BBG_LONDON", "investmentDiscretion": "Sole", "investmentVehicleType": "ETF", "investmentVehicle": "Onshore Mutual Fund - Taxable", "pricingSource": "INST_GC", "sourcingOffice": "Invesco US WMI (Wealth Mgmt Intermediaries) - ST", "taxLotMethodSellingConventionDescription": "FIFO", "taxlotmethodsellingconventioncode": "FIFO", "taxStatusAccount": "Taxable", "terminationMarketValue": "", "clientId": "1-CB57Q", "clientName": "Invesco PowerShares Capital Management LLC", "crsClassification": "", "emirClearingStatus": "", "emirEntityTypeIndicator": "", "emirReportingStatus": "", "emirAboveClearingThresholdIndicator": "", "emirCommercialTreasuryLinkedIndicator": "", "emirLeiInvestmentManager": "", "emirLeiIvzManagementCompany": "", "emirReportingFirmCorporateSector": "", "emirWhoIsResponsibleForTradeReporting": "", "erisaClassification": "", "fatcaChapter4Classification": "", "fatcaComments": "", "fatcaIdentifier": "", "fatcaOnboardingAgent": "", "fatcaRegistrationApproach": "", "fatcaReporting": "", "fatcaReportingAgent": "", "fatcaType": "", "fatcaWithholdingAgent": "", "fatcaEntityNumber": "1-1DD3PBF", "fatcaLocalEntityName": "", "fatcaNextRenewalDate": "", "investmentStrategy": {"investmentStrategyId": 151, "strategyCodeRowId": "1-1ECTVZ0", "investmentStrategyCode": "PWSUSHYBV", "investmentStrategyName": "IETF- US High Yield Bond Value", "managedBusinessUnitCode": "Americas", "investmentCenter": "Invesco ETF", "investmentTeamRollupCode": "IETF - Invesco Americas ETF", "investmentTeam": "IETF - Fixed Income ETF", "assetClassMainRollupCode": "Fixed Income", "geographicalFocusCode": "United States", "managementStyleCode": "Passive", "solutionRollupCode": "", "solutionCategoriesCode": "", "marketCapitalizationCode": "Non Equities", "environmentalSocialAndGovernanceCriteriaIndicator": "Non-ESG", "factorBasedDescription": "Traditional Beta", "fundamentalDescription": "", "persistent": "", "superCompositeName": "", "representativeFundName": "", "strategyCompositeCode": "", "strategyCompositeName": "", "assetSubClass": "", "assetSubSubClass": "", "assetSubSubSubClass": "", "sourceCode": "ATLAS"}}, "shareClassCharges": [{"shareClassChargeTypeId": "1-20B7KVU", "sourceCode": "ATLAS", "shareClassChargeType": "Net Expense Ratio", "shareClassChargePercentage": 0.23, "shareClassChargeDescription": "0.23"}, {"shareClassChargeTypeId": "1-HXLVB4", "sourceCode": "ATLAS", "shareClassChargeType": "Total Expense Ratio", "shareClassChargePercentage": 0.23, "shareClassChargeDescription": "0.23"}], "aliases": [{"masterEntityId": "09TB0317XXSCETF", "effectiveDate": "2019-09-30", "entityType": "SHRCLS", "aliasType": "Cadis Id", "aliasValue": "1767755", "entityId": 34}, {"masterEntityId": "09TB0317XXSCETF", "effectiveDate": "2019-09-30", "entityType": "SHRCLS", "aliasType": "Cusip", "aliasValue": "46139W403", "entityId": 34}, {"masterEntityId": "09TB0317XXSCETF", "effectiveDate": "2019-09-30", "entityType": "SHRCLS", "aliasType": "Edgar Class ID", "aliasValue": "C000201204", "entityId": 34}, {"masterEntityId": "09TB0317XXSCETF", "effectiveDate": "2019-09-30", "entityType": "SHRCLS", "aliasType": "Fund Station Id", "aliasValue": "2501", "entityId": 34}, {"masterEntityId": "09TB0317XXSCETF", "effectiveDate": "2019-09-30", "entityType": "SHRCLS", "aliasType": "Fundstation Number", "aliasValue": "57596602", "entityId": 34}, {"masterEntityId": "09TB0317XXSCETF", "effectiveDate": "2019-09-30", "entityType": "SHRCLS", "aliasType": "Fund Symbol", "aliasValue": "IHYV", "entityId": 34}, {"masterEntityId": "09TB0317XXSCETF", "effectiveDate": "2019-09-30", "entityType": "SHRCLS", "aliasType": "iNAV", "aliasValue": "IHYV.IV", "entityId": 34}, {"masterEntityId": "09TB0317XXSCETF", "effectiveDate": "2019-09-30", "entityType": "SHRCLS", "aliasType": "ISIN", "aliasValue": "US46139W4033", "entityId": 34}, {"masterEntityId": "09TB0317XXSCETF", "effectiveDate": "2019-09-30", "entityType": "SHRCLS", "aliasType": "Sedol", "aliasValue": "BF2NB19", "entityId": 34}, {"masterEntityId": "09TB0317XXSCETF", "effectiveDate": "2019-09-30", "entityType": "SHRCLS", "aliasType": "TA Code", "aliasValue": "301250", "entityId": 34}, {"masterEntityId": "09TB0317XXSCETF", "effectiveDate": "2019-09-30", "entityType": "SHRCLS", "aliasType": "Viaduct Share Class ID", "aliasValue": "1-1DD3PHY", "entityId": 34}, {"masterEntityId": "09TB0317XXSCETF", "effectiveDate": "2019-09-30", "entityType": "SHRCLS", "aliasType": "Ticker", "aliasValue": "IHYV", "entityId": 34}], "benchmarkRelationships": [{"benchmarkOrdinalNumber": 1, "benchmark": {"benchmarkId": "EGL_250139", "indexCode": "EGL_250139", "edlMasterIndexIdentifier": "EGL_250139", "indexStatus": "", "indexShortName": "Markit iBoxx USD Liquid High Yield Index-TR", "indexCurrencyCode": "USD", "inceptionDate": "1998-12-31", "performanceStartDate": "1998-12-31", "terminationDate": "", "indexFullName": "Markit iBoxx USD Liquid High Yield Index-TR", "indexProvider": "", "crossReferences": [{"crossReferenceType": "BLOOMBERG", "crossReferenceCode": "IBOXHY-USD"}, {"crossReferenceType": "FPS_IX", "crossReferenceCode": "27032"}, {"crossReferenceType": "ZEPHYR_DLY", "crossReferenceCode": "250139.eid"}, {"crossReferenceType": "ZEPHYR_MTH", "crossReferenceCode": "250139.eim"}]}}, {"benchmarkOrdinalNumber": 6, "benchmark": {"benchmarkId": "EGL_248591", "indexCode": "EGL_248591", "edlMasterIndexIdentifier": "EGL_248591", "indexStatus": "", "indexShortName": "Invesco High Yield Value Index-TR", "indexCurrencyCode": "USD", "inceptionDate": "2007-12-31", "performanceStartDate": "2007-12-31", "terminationDate": "", "indexFullName": "Invesco High Yield Value Index-TR", "indexProvider": "", "crossReferences": [{"crossReferenceType": "FPS_IX", "crossReferenceCode": "27034"}, {"crossReferenceType": "MANUFACTURER_ID", "crossReferenceCode": "IIHV"}, {"crossReferenceType": "RIMES", "crossReferenceCode": "IIHYV.GROSS.USD"}, {"crossReferenceType": "RIMES_INDX", "crossReferenceCode": "INVIC1-IIHYV-TR$"}, {"crossReferenceType": "ZEPHYR_DLY", "crossReferenceCode": "248591.eid"}, {"crossReferenceType": "ZEPHYR_MTH", "crossReferenceCode": "248591.eim"}]}}, {"benchmarkOrdinalNumber": 10, "benchmark": {"benchmarkId": "EGL_248591", "indexCode": "EGL_248591", "edlMasterIndexIdentifier": "EGL_248591", "indexStatus": "", "indexShortName": "Invesco High Yield Value Index-TR", "indexCurrencyCode": "USD", "inceptionDate": "2007-12-31", "performanceStartDate": "2007-12-31", "terminationDate": "", "indexFullName": "Invesco High Yield Value Index-TR", "indexProvider": "", "crossReferences": [{"crossReferenceType": "FPS_IX", "crossReferenceCode": "27034"}, {"crossReferenceType": "MANUFACTURER_ID", "crossReferenceCode": "IIHV"}, {"crossReferenceType": "RIMES", "crossReferenceCode": "IIHYV.GROSS.USD"}, {"crossReferenceType": "RIMES_INDX", "crossReferenceCode": "INVIC1-IIHYV-TR$"}, {"crossReferenceType": "ZEPHYR_DLY", "crossReferenceCode": "248591.eid"}, {"crossReferenceType": "ZEPHYR_MTH", "crossReferenceCode": "248591.eim"}]}}, {"benchmarkOrdinalNumber": 8, "benchmark": {"benchmarkId": "EGL_20445", "indexCode": "EGL_20445", "edlMasterIndexIdentifier": "EGL_20445", "indexStatus": "", "indexShortName": "T-Bill 3 Month Index (Lipper)", "indexCurrencyCode": "USD", "inceptionDate": "1956-12-31", "performanceStartDate": "1956-12-31", "terminationDate": "", "indexFullName": "T-Bill 3 Month Index (Lipper)", "indexProvider": "", "crossReferences": [{"crossReferenceType": "FPS_IX", "crossReferenceCode": "749"}, {"crossReferenceType": "LANA", "crossReferenceCode": "HGKJ"}, {"crossReferenceType": "PERFORMA_EGL", "crossReferenceCode": "EGL_20445"}, {"crossReferenceType": "ZEPHYR_DLY", "crossReferenceCode": "20445.eid"}, {"crossReferenceType": "ZEPHYR_MTH", "crossReferenceCode": "20445.eim"}]}}]}