{"accountId": "775", "edlMasterAccountIdentifier": "09TBBUYBXX", "effectiveDate": "9999-12-31", "Analytics": {"FixedIncome": [], "Equity": [{"masterentityid": "09TBBUYBAA", "entityType": "ACCT", "entityName": "To be added at a later date.", "benchmarkOrdinal": 0, "estimatedLongTermGrowthPercent": 64.1048151503191, "forwardGrowth12MonthPercent": "", "epsFy1OverFy0GrowthPercent": "", "epsFy2OverFy1GrowthPercent": "", "epsLastQuarterOverQuarterGrowthPercent": "", "epsNextQuarterOverQuarterGrowthPercent": "", "salesPerShareGrowthRate3YearPercent": "", "epsGrowth3YearPercent": "", "epsGrowth5YearPercent": "", "dividendGrowth1YearPercent": "", "dividendGrowth3YearPercent": "", "dividendGrowth5YearPercent": 14.7388672691351, "dividendYieldGrowth1YearPercent": "", "dividendYieldGrowth3YearPercent": "", "dividendYieldGrowth5YearPercent": "", "dividendYieldTrailing12MonthPercent": "", "peForward1YearExNegativeRatio": "", "peForward1YearRatio": "", "peForward2YearExNegativeRatio": "", "peForward2YearRatio": "", "peForward12MonthExNegativeRatio": "", "peForward12MonthRatio": "", "peTrailing12MonthExNegativeRatio": "", "peTrailing12MonthRatio": 8.16027165364569, "priceToCashFlowRatio": "", "priceToSalesRatio": "", "organizationReturnOnInvestmentPercent": "", "longTermDebtToCapitalRatio": "", "marketCapitalizationWeightedAverage": "", "marketCapitalizationUnweightedAverage": "", "marketCapitalizationMedian": "", "marketCapitalizationLargest": "", "marketCapitalizationSmallest": "", "priceToBookRatio": 4.99882930213744, "cashFlowYieldAmount": "", "debtToEquityRatio": "", "epsPreviousYearPercent": "", "payoutRatio": "", "roe5YearPercent": "", "sustainableGrowthPercent": "", "totalSharesOutstandingQuantity": "", "average20DayTradedVolumeValue": ""}]}}