{"effectiveDate": "2019-09-30", "edlMasterShareClassIdentifier": "09TB0DBAXXSCETF", "shareClassFullName": "Invesco DB Agriculture Fund", "accountId": 227, "shareClassCurrency": "USD", "shareClassInceptionDate": "2007-01-05", "performanceInceptionDate": "2007-01-05", "shareClassShortName": "Invesco DB Agriculture Fund", "shareClassStatus": "Open", "shareClassTerminationDate": "", "primaryShareClassIndicator": "True", "atlasAliasValueId": "1-5HRK-145", "shareClassId": 616, "grossOrNetIndicator": "", "hedgedIndicator": "", "hedgedCurrencyCode": "", "isaEligible": "", "sippEligible": "", "ucitsCompliant": "", "dividendTreatment": "", "dividendSchedule": "", "ukReportingStatus": "", "registrationMatrix": [], "yields": {"secYield30Day": 0, "secUnsubsidizedYield30Day": 0}, "account": {"accountId": 227, "effectiveDate": "2019-09-30", "atlasPartyId": 32, "subType": "ACCT.FUND", "accountCode": "", "accountName": "Invesco DB Agriculture Fund", "accountNumber": "DBA", "accountCurrencyCode": "USD", "domicileCountryCode": "US", "accountFiscalYearEnd": "", "legalEntityIdentifier": "549300CW37D800HX4P40", "numberOfShareclasses": "", "performanceStartDate": "2007-01-05", "proxyVotingAuthority": "Sole", "accountStatus": "Open", "terminationDate": "", "accountLevelOfService": "ETF", "fundOfFunds": "", "accountOpenDate": "2007-01-05", "edlMasterAccountIdentifier": "09TB0DBAXX", "accountingBasisName": "GAAP", "managementFeeType": "NA", "securityLendingAssetTypes": "", "securityLendingParticipationFlag": "", "accountShortName": "", "accountTerminationReason": "", "taxId": "NA", "fxRateSource": "BBG_LONDON", "investmentDiscretion": "Sole", "investmentVehicleType": "ETF", "investmentVehicle": "Onshore Mutual Fund - Taxable", "pricingSource": "INST_GC", "sourcingOffice": "Invesco US WMI (Wealth Mgmt Intermediaries) - ST", "taxLotMethodSellingConventionDescription": "FIFO", "taxlotmethodsellingconventioncode": "FIFO", "taxStatusAccount": "Taxable", "terminationMarketValue": "", "clientId": "1-CB57Q", "clientName": "Invesco PowerShares Capital Management LLC", "crsClassification": "Investment Entity located in a Non-Participating Jurisdiction and managed by another FI", "emirClearingStatus": "", "emirEntityTypeIndicator": "", "emirReportingStatus": "", "emirAboveClearingThresholdIndicator": "", "emirCommercialTreasuryLinkedIndicator": "", "emirLeiInvestmentManager": "", "emirLeiIvzManagementCompany": "", "emirReportingFirmCorporateSector": "", "emirWhoIsResponsibleForTradeReporting": "", "erisaClassification": "", "fatcaChapter4Classification": "", "fatcaComments": "", "fatcaIdentifier": "", "fatcaOnboardingAgent": "", "fatcaRegistrationApproach": "", "fatcaReporting": "", "fatcaReportingAgent": "", "fatcaType": "", "fatcaWithholdingAgent": "", "fatcaEntityNumber": "1-462W-24", "fatcaLocalEntityName": "", "fatcaNextRenewalDate": "", "investmentStrategy": {"investmentStrategyId": 413, "strategyCodeRowId": "1-57YZ-384", "investmentStrategyCode": "PWSPWR0023", "investmentStrategyName": "IETF- DB Agriculture", "managedBusinessUnitCode": "Americas", "investmentCenter": "Invesco ETF", "investmentTeamRollupCode": "IETF - Invesco Americas ETF", "investmentTeam": "IETF - Alternative ETF", "assetClassMainRollupCode": "Alternative", "geographicalFocusCode": "Global", "managementStyleCode": "Passive", "solutionRollupCode": "", "solutionCategoriesCode": "", "marketCapitalizationCode": "Non Equities", "environmentalSocialAndGovernanceCriteriaIndicator": "", "factorBasedDescription": "Smart Beta", "fundamentalDescription": "", "persistent": "", "superCompositeName": "", "representativeFundName": "", "strategyCompositeCode": "", "strategyCompositeName": "", "assetSubClass": "Commodity", "assetSubSubClass": "Commodity", "assetSubSubSubClass": "Commodity", "sourceCode": "ATLAS"}}, "shareClassCharges": [], "aliases": [{"masterEntityId": "09TB0DBAXXSCETF", "effectiveDate": "2019-09-30", "entityType": "SHRCLS", "aliasType": "Cadis Id", "aliasValue": "1728269", "entityId": 616}, {"masterEntityId": "09TB0DBAXXSCETF", "effectiveDate": "2019-09-30", "entityType": "SHRCLS", "aliasType": "Cusip", "aliasValue": "46140H106", "entityId": 616}, {"masterEntityId": "09TB0DBAXXSCETF", "effectiveDate": "2019-09-30", "entityType": "SHRCLS", "aliasType": "Fund Station Id", "aliasValue": "4577", "entityId": 616}, {"masterEntityId": "09TB0DBAXXSCETF", "effectiveDate": "2019-09-30", "entityType": "SHRCLS", "aliasType": "Fundstation Number", "aliasValue": "57700502", "entityId": 616}, {"masterEntityId": "09TB0DBAXXSCETF", "effectiveDate": "2019-09-30", "entityType": "SHRCLS", "aliasType": "Fund Symbol", "aliasValue": "DBA", "entityId": 616}, {"masterEntityId": "09TB0DBAXXSCETF", "effectiveDate": "2019-09-30", "entityType": "SHRCLS", "aliasType": "iNAV", "aliasValue": "DBA.IV", "entityId": 616}, {"masterEntityId": "09TB0DBAXXSCETF", "effectiveDate": "2019-09-30", "entityType": "SHRCLS", "aliasType": "ISIN", "aliasValue": "US46140H1068", "entityId": 616}, {"masterEntityId": "09TB0DBAXXSCETF", "effectiveDate": "2019-09-30", "entityType": "SHRCLS", "aliasType": "Sedol", "aliasValue": "BZ03T17", "entityId": 616}, {"masterEntityId": "09TB0DBAXXSCETF", "effectiveDate": "2019-09-30", "entityType": "SHRCLS", "aliasType": "TA Code", "aliasValue": "301128", "entityId": 616}, {"masterEntityId": "09TB0DBAXXSCETF", "effectiveDate": "2019-09-30", "entityType": "SHRCLS", "aliasType": "Ticker", "aliasValue": "DBA", "entityId": 616}, {"masterEntityId": "09TB0DBAXXSCETF", "effectiveDate": "2019-09-30", "entityType": "SHRCLS", "aliasType": "Viaduct Share Class ID", "aliasValue": "1-5HRK-145", "entityId": 616}], "benchmarkRelationships": [{"benchmarkOrdinalNumber": 2, "benchmark": {"benchmarkId": "EGL_232050", "indexCode": "EGL_232050", "edlMasterIndexIdentifier": "EGL_232050", "indexStatus": "", "indexShortName": "S&P GSCI Agriculture Index-TR", "indexCurrencyCode": "USD", "inceptionDate": "1969-12-31", "performanceStartDate": "1991-05-01", "terminationDate": "", "indexFullName": "S&P GSCI Agriculture Index-TR", "indexProvider": "S&P", "crossReferences": [{"crossReferenceType": "BLOOMBERG", "crossReferenceCode": "SPGSAGTR-USD"}, {"crossReferenceType": "FPS_IX", "crossReferenceCode": "22562"}, {"crossReferenceType": "ZEPHYR_DLY", "crossReferenceCode": "232050.eid"}, {"crossReferenceType": "ZEPHYR_MTH", "crossReferenceCode": "232050.eim"}]}}, {"benchmarkOrdinalNumber": 10, "benchmark": {"benchmarkId": "EGL_222598", "indexCode": "EGL_222598", "edlMasterIndexIdentifier": "EGL_222598", "indexStatus": "", "indexShortName": "Blended DBLCI Diversified Agriculture Excess Return Index", "indexCurrencyCode": "USD", "inceptionDate": "1988-12-03", "performanceStartDate": "1988-12-03", "terminationDate": "", "indexFullName": "Blended DBLCI Diversified Agriculture Excess Return Index", "indexProvider": "", "crossReferences": [{"crossReferenceType": "FPS_IX", "crossReferenceCode": "19548"}, {"crossReferenceType": "FS_HOU", "crossReferenceCode": "14158"}, {"crossReferenceType": "FS_HOU_SK", "crossReferenceCode": "50070076"}, {"crossReferenceType": "PERFORMA_EGL", "crossReferenceCode": "EGL_222598"}, {"crossReferenceType": "ZEPHYR_DLY", "crossReferenceCode": "222598.eid"}, {"crossReferenceType": "ZEPHYR_MTH", "crossReferenceCode": "222598.eim"}]}}, {"benchmarkOrdinalNumber": 6, "benchmark": {"benchmarkId": "EGL_222598", "indexCode": "EGL_222598", "edlMasterIndexIdentifier": "EGL_222598", "indexStatus": "", "indexShortName": "Blended DBLCI Diversified Agriculture Excess Return Index", "indexCurrencyCode": "USD", "inceptionDate": "1988-12-03", "performanceStartDate": "1988-12-03", "terminationDate": "", "indexFullName": "Blended DBLCI Diversified Agriculture Excess Return Index", "indexProvider": "", "crossReferences": [{"crossReferenceType": "FPS_IX", "crossReferenceCode": "19548"}, {"crossReferenceType": "FS_HOU", "crossReferenceCode": "14158"}, {"crossReferenceType": "FS_HOU_SK", "crossReferenceCode": "50070076"}, {"crossReferenceType": "PERFORMA_EGL", "crossReferenceCode": "EGL_222598"}, {"crossReferenceType": "ZEPHYR_DLY", "crossReferenceCode": "222598.eid"}, {"crossReferenceType": "ZEPHYR_MTH", "crossReferenceCode": "222598.eim"}]}}, {"benchmarkOrdinalNumber": 5, "benchmark": {"benchmarkId": "EGL_222583", "indexCode": "EGL_222583", "edlMasterIndexIdentifier": "EGL_222583", "indexStatus": "", "indexShortName": "DBIQ Diversified Agriculture Index Excess Return", "indexCurrencyCode": "USD", "inceptionDate": "1988-12-02", "performanceStartDate": "2010-10-07", "terminationDate": "", "indexFullName": "DBIQ Diversified Agriculture Index Excess Return", "indexProvider": "Deutsche Bank", "crossReferences": [{"crossReferenceType": "BLOOMBERG", "crossReferenceCode": "DBLCDBAE-USD"}, {"crossReferenceType": "FPS_IX", "crossReferenceCode": "19532"}, {"crossReferenceType": "FS_HOU", "crossReferenceCode": "14139"}, {"crossReferenceType": "FS_HOU_SK", "crossReferenceCode": "50070070"}, {"crossReferenceType": "PERFORMA_EGL", "crossReferenceCode": "EGL_222583"}, {"crossReferenceType": "RIMES", "crossReferenceCode": "DBLCDBAE.EXCESS.USD"}, {"crossReferenceType": "ZEPHYR_DLY", "crossReferenceCode": "222583.eid"}, {"crossReferenceType": "ZEPHYR_MTH", "crossReferenceCode": "222583.eim"}]}}, {"benchmarkOrdinalNumber": 8, "benchmark": {"benchmarkId": "EGL_20445", "indexCode": "EGL_20445", "edlMasterIndexIdentifier": "EGL_20445", "indexStatus": "", "indexShortName": "T-Bill 3 Month Index (Lipper)", "indexCurrencyCode": "USD", "inceptionDate": "1956-12-31", "performanceStartDate": "1956-12-31", "terminationDate": "", "indexFullName": "T-Bill 3 Month Index (Lipper)", "indexProvider": "", "crossReferences": [{"crossReferenceType": "FPS_IX", "crossReferenceCode": "749"}, {"crossReferenceType": "LANA", "crossReferenceCode": "HGKJ"}, {"crossReferenceType": "PERFORMA_EGL", "crossReferenceCode": "EGL_20445"}, {"crossReferenceType": "ZEPHYR_DLY", "crossReferenceCode": "20445.eid"}, {"crossReferenceType": "ZEPHYR_MTH", "crossReferenceCode": "20445.eim"}]}}, {"benchmarkOrdinalNumber": 1, "benchmark": {"benchmarkId": "EGL_54631", "indexCode": "EGL_54631", "edlMasterIndexIdentifier": "EGL_54631", "indexStatus": "", "indexShortName": "Blended DBLCI Diversified Agriculture Total Return Index", "indexCurrencyCode": "USD", "inceptionDate": "1988-12-03", "performanceStartDate": "1988-12-03", "terminationDate": "", "indexFullName": "Blended DBLCI Diversified Agriculture Total Return Index", "indexProvider": "", "crossReferences": [{"crossReferenceType": "FPS_IX", "crossReferenceCode": "11634"}, {"crossReferenceType": "PERFORMA_EGL", "crossReferenceCode": "EGL_54631"}, {"crossReferenceType": "ZEPHYR_DLY", "crossReferenceCode": "54631.eid"}, {"crossReferenceType": "ZEPHYR_MTH", "crossReferenceCode": "54631.eim"}]}}]}