{"masterEntityId": "09TBEQQQXXSCETFCHFH", "effectiveDate": "2019-09-30", "fiscalYearEnd": "2015-09-30", "performanceInceptionDate": "2017-10-17", "performanceRestructureDate": "", "performance": [{"masterEntityId": "09TBEQQQXXSCETFCHFH", "entityName": "Invesco EQQQ NASDAQ-100 UCITS ETF - CHF Hedged UCITS ETF", "entityType": "SHARECLASS", "benchmarkOrdinal": "", "performanceCommitFlag": "P", "performanceType": "ATH", "performanceSourceCode": "Eagle PACE", "currencyCode": "CHF", "grossNet": "GROSS", "cumulative": {"m1": "", "m3": "", "m6": "", "m12": "", "qtd": "", "ytd": "", "fytd": "", "y1": "", "y2": "", "y3": "", "y5": "", "y10": "", "rtd": "", "itd": ""}, "annualized": {"m1": "", "m3": "", "m6": "", "m12": "", "qtd": "", "ytd": "", "fytd": "", "y1": "", "y2": "", "y3": "", "y5": "", "y10": "", "rtd": "", "itd": ""}}, {"masterEntityId": "09TBEQQQXXSCETFCHFH", "entityName": "Invesco EQQQ NASDAQ-100 UCITS ETF - CHF Hedged UCITS ETF", "entityType": "SHARECLASS", "benchmarkOrdinal": "", "performanceCommitFlag": "P", "performanceType": "ATS", "performanceSourceCode": "Eagle PACE", "currencyCode": "CHF", "grossNet": "GROSS", "cumulative": {"m1": "", "m3": "", "m6": "", "m12": "", "qtd": "", "ytd": "", "fytd": "", "y1": "", "y2": "", "y3": "", "y5": "", "y10": "", "rtd": "", "itd": ""}, "annualized": {"m1": "", "m3": "", "m6": "", "m12": "", "qtd": "", "ytd": "", "fytd": "", "y1": "", "y2": "", "y3": "", "y5": "", "y10": "", "rtd": "", "itd": ""}}, {"masterEntityId": "09TBEQQQXXSCETFCHFH", "entityName": "Invesco EQQQ NASDAQ-100 UCITS ETF - CHF Hedged UCITS ETF", "entityType": "SHARECLASS", "benchmarkOrdinal": "", "performanceCommitFlag": "P", "performanceType": "EXTNAV", "performanceSourceCode": "Eagle PACE", "currencyCode": "CHF", "grossNet": "GROSS", "cumulative": {"m1": 0.536352, "m3": 0.29648, "m6": 3.609712, "m12": -1.157744, "qtd": 0.29648, "ytd": 20.025952, "fytd": "", "y1": -1.157744, "y2": "", "y3": "", "y5": "", "y10": "", "rtd": "", "itd": 20.640624}, "annualized": {"m1": 0.536352, "m3": 0.29648, "m6": 3.609712, "m12": -1.157744, "qtd": 0.29648, "ytd": 20.025952, "fytd": "", "y1": -1.157744, "y2": "", "y3": "", "y5": "", "y10": "", "rtd": "", "itd": 10.077764431268}}, {"masterEntityId": "09TBEQQQXXSCETFCHFH", "entityName": "Invesco EQQQ NASDAQ-100 UCITS ETF - CHF Hedged UCITS ETF", "entityType": "SHARECLASS", "benchmarkOrdinal": "", "performanceCommitFlag": "P", "performanceType": "NAV", "performanceSourceCode": "Eagle PACE", "currencyCode": "CHF", "grossNet": "GROSS", "cumulative": {"m1": "", "m3": "", "m6": "", "m12": "", "qtd": "", "ytd": "", "fytd": "", "y1": "", "y2": "", "y3": "", "y5": "", "y10": "", "rtd": "", "itd": ""}, "annualized": {"m1": "", "m3": "", "m6": "", "m12": "", "qtd": "", "ytd": "", "fytd": "", "y1": "", "y2": "", "y3": "", "y5": "", "y10": "", "rtd": "", "itd": ""}}, {"masterEntityId": "09TBEQQQXXSCETFCHFH", "entityName": "Invesco EQQQ NASDAQ-100 UCITS ETF - CHF Hedged UCITS ETF", "entityType": "SHARECLASS", "benchmarkOrdinal": "", "performanceCommitFlag": "P", "performanceType": "ATH", "performanceSourceCode": "Eagle PACE", "currencyCode": "CHF", "grossNet": "NET", "cumulative": {"m1": 0.506368, "m3": "", "m6": "", "m12": "", "qtd": "", "ytd": 19.756096, "fytd": "", "y1": -1.517552, "y2": "", "y3": "", "y5": "", "y10": "", "rtd": "", "itd": ""}, "annualized": {"m1": 0.506368, "m3": "", "m6": "", "m12": "", "qtd": "", "ytd": 19.756096, "fytd": "", "y1": -1.517552, "y2": "", "y3": "", "y5": "", "y10": "", "rtd": "", "itd": 9.748312043446}}, {"masterEntityId": "09TBEQQQXXSCETFCHFH", "entityName": "Invesco EQQQ NASDAQ-100 UCITS ETF - CHF Hedged UCITS ETF", "entityType": "SHARECLASS", "benchmarkOrdinal": "", "performanceCommitFlag": "P", "performanceType": "ATS", "performanceSourceCode": "Eagle PACE", "currencyCode": "CHF", "grossNet": "NET", "cumulative": {"m1": 0.3012256, "m3": "", "m6": "", "m12": "", "qtd": "", "ytd": 11.693072704, "fytd": "", "y1": -0.895756736, "y2": "", "y3": "", "y5": "", "y10": "", "rtd": "", "itd": ""}, "annualized": {"m1": 0.3012256, "m3": "", "m6": "", "m12": "", "qtd": "", "ytd": 11.693072704, "fytd": "", "y1": -0.895756736, "y2": "", "y3": "", "y5": "", "y10": "", "rtd": "", "itd": 7.504791292542}}, {"masterEntityId": "09TBEQQQXXSCETFCHFH", "entityName": "Invesco EQQQ NASDAQ-100 UCITS ETF - CHF Hedged UCITS ETF", "entityType": "SHARECLASS", "benchmarkOrdinal": "", "performanceCommitFlag": "P", "performanceType": "EXTNAV", "performanceSourceCode": "Eagle PACE", "currencyCode": "CHF", "grossNet": "NET", "cumulative": {"m1": 0.506368, "m3": 0.206528, "m6": 3.429808, "m12": -1.517552, "qtd": 0.206528, "ytd": 19.756096, "fytd": "", "y1": -1.517552, "y2": "", "y3": "", "y5": "", "y10": "", "rtd": "", "itd": 19.936}, "annualized": {"m1": 0.506368, "m3": 0.206528, "m6": 3.429808, "m12": -1.517552, "qtd": 0.206528, "ytd": 19.756096, "fytd": "", "y1": -1.517552, "y2": "", "y3": "", "y5": "", "y10": "", "rtd": "", "itd": 9.748312043446}}, {"masterEntityId": "09TBEQQQXXSCETFCHFH", "entityName": "Invesco EQQQ NASDAQ-100 UCITS ETF - CHF Hedged UCITS ETF", "entityType": "SHARECLASS", "benchmarkOrdinal": "", "performanceCommitFlag": "P", "performanceType": "NAV", "performanceSourceCode": "Eagle PACE", "currencyCode": "CHF", "grossNet": "NET", "cumulative": {"m1": 0.506368, "m3": "", "m6": "", "m12": "", "qtd": "", "ytd": 19.756096, "fytd": "", "y1": -1.517552, "y2": "", "y3": "", "y5": "", "y10": "", "rtd": "", "itd": ""}, "annualized": {"m1": 0.506368, "m3": "", "m6": "", "m12": "", "qtd": "", "ytd": 19.756096, "fytd": "", "y1": -1.517552, "y2": "", "y3": "", "y5": "", "y10": "", "rtd": "", "itd": 9.748312043446}}, {"masterEntityId": "EGL_251759", "entityName": "S&P 500 Index-NR-CHFH-USDR", "entityType": "BENCHMARK", "benchmarkOrdinal": 6, "performanceCommitFlag": "P", "performanceType": "ATH", "performanceSourceCode": "Eagle PACE", "currencyCode": "CHF", "grossNet": "", "cumulative": {"m1": "", "m3": "", "m6": "", "qtd": "", "ytd": "", "fytd": "", "y1": "", "y2": "", "y3": "", "y5": "", "y10": "", "rtd": "", "itd": ""}, "annualized": {"m1": "", "m3": "", "m6": "", "qtd": "", "ytd": "", "fytd": "", "y1": "", "y2": "", "y3": "", "y5": "", "y10": "", "rtd": "", "itd": ""}}, {"masterEntityId": "EGL_251777", "entityName": "Nasdaq 100 Index NR-CHFH-USDR", "entityType": "BENCHMARK", "benchmarkOrdinal": 1, "performanceCommitFlag": "P", "performanceType": "ATH", "performanceSourceCode": "Eagle PACE", "currencyCode": "CHF", "grossNet": "", "cumulative": {"m1": "", "m3": "", "m6": "", "qtd": "", "ytd": "", "fytd": "", "y1": "", "y2": "", "y3": "", "y5": "", "y10": "", "rtd": "", "itd": ""}, "annualized": {"m1": "", "m3": "", "m6": "", "qtd": "", "ytd": "", "fytd": "", "y1": "", "y2": "", "y3": "", "y5": "", "y10": "", "rtd": "", "itd": ""}}, {"masterEntityId": "EGL_251759", "entityName": "S&P 500 Index-NR-CHFH-USDR", "entityType": "BENCHMARK", "benchmarkOrdinal": 6, "performanceCommitFlag": "P", "performanceType": "ATS", "performanceSourceCode": "Eagle PACE", "currencyCode": "CHF", "grossNet": "", "cumulative": {"m1": "", "m3": "", "m6": "", "qtd": "", "ytd": "", "fytd": "", "y1": "", "y2": "", "y3": "", "y5": "", "y10": "", "rtd": "", "itd": ""}, "annualized": {"m1": "", "m3": "", "m6": "", "qtd": "", "ytd": "", "fytd": "", "y1": "", "y2": "", "y3": "", "y5": "", "y10": "", "rtd": "", "itd": ""}}, {"masterEntityId": "EGL_251777", "entityName": "Nasdaq 100 Index NR-CHFH-USDR", "entityType": "BENCHMARK", "benchmarkOrdinal": 1, "performanceCommitFlag": "P", "performanceType": "ATS", "performanceSourceCode": "Eagle PACE", "currencyCode": "CHF", "grossNet": "", "cumulative": {"m1": "", "m3": "", "m6": "", "qtd": "", "ytd": "", "fytd": "", "y1": "", "y2": "", "y3": "", "y5": "", "y10": "", "rtd": "", "itd": ""}, "annualized": {"m1": "", "m3": "", "m6": "", "qtd": "", "ytd": "", "fytd": "", "y1": "", "y2": "", "y3": "", "y5": "", "y10": "", "rtd": "", "itd": ""}}, {"masterEntityId": "EGL_251777", "entityName": "Nasdaq 100 Index NR-CHFH-USDR", "entityType": "BENCHMARK", "benchmarkOrdinal": 1, "performanceCommitFlag": "P", "performanceType": "EXTNAV", "performanceSourceCode": "Eagle PACE", "currencyCode": "CHF", "grossNet": "", "cumulative": {"m1": "", "m3": "", "m6": "", "qtd": "", "ytd": "", "fytd": "", "y1": "", "y2": "", "y3": "", "y5": "", "y10": "", "rtd": "", "itd": 28.452138222059}, "annualized": {"m1": "", "m3": "", "m6": "", "qtd": "", "ytd": "", "fytd": "", "y1": "", "y2": "", "y3": "", "y5": "", "y10": "", "rtd": "", "itd": 28.452138222059}}, {"masterEntityId": "EGL_251759", "entityName": "S&P 500 Index-NR-CHFH-USDR", "entityType": "BENCHMARK", "benchmarkOrdinal": 6, "performanceCommitFlag": "P", "performanceType": "EXTNAV", "performanceSourceCode": "Eagle PACE", "currencyCode": "CHF", "grossNet": "", "cumulative": {"m1": "", "m3": "", "m6": "", "qtd": "", "ytd": "", "fytd": "", "y1": "", "y2": "", "y3": "", "y5": "", "y10": "", "rtd": "", "itd": 19.512196189504}, "annualized": {"m1": "", "m3": "", "m6": "", "qtd": "", "ytd": "", "fytd": "", "y1": "", "y2": "", "y3": "", "y5": "", "y10": "", "rtd": "", "itd": 19.512196189504}}, {"masterEntityId": "EGL_251759", "entityName": "S&P 500 Index-NR-CHFH-USDR", "entityType": "BENCHMARK", "benchmarkOrdinal": 6, "performanceCommitFlag": "P", "performanceType": "NAV", "performanceSourceCode": "Eagle PACE", "currencyCode": "CHF", "grossNet": "", "cumulative": {"m1": "", "m3": "", "m6": "", "qtd": "", "ytd": "", "fytd": "", "y1": "", "y2": "", "y3": "", "y5": "", "y10": "", "rtd": "", "itd": ""}, "annualized": {"m1": "", "m3": "", "m6": "", "qtd": "", "ytd": "", "fytd": "", "y1": "", "y2": "", "y3": "", "y5": "", "y10": "", "rtd": "", "itd": ""}}, {"masterEntityId": "EGL_251777", "entityName": "Nasdaq 100 Index NR-CHFH-USDR", "entityType": "BENCHMARK", "benchmarkOrdinal": 1, "performanceCommitFlag": "P", "performanceType": "NAV", "performanceSourceCode": "Eagle PACE", "currencyCode": "CHF", "grossNet": "", "cumulative": {"m1": "", "m3": "", "m6": "", "qtd": "", "ytd": "", "fytd": "", "y1": "", "y2": "", "y3": "", "y5": "", "y10": "", "rtd": "", "itd": ""}, "annualized": {"m1": "", "m3": "", "m6": "", "qtd": "", "ytd": "", "fytd": "", "y1": "", "y2": "", "y3": "", "y5": "", "y10": "", "rtd": "", "itd": ""}}]}