{"masterEntityId": "09TBEQQQXX", "accountName": "Invesco EQQQ NASDAQ-100 UCITS ETF", "accountId": "611", "effectiveDate": "9999-12-31", "weightedHoldingSchemes": [{"schemeId": "HOLDINGS_TOP10", "schemeType": "HOLDINGS", "levelDepth": 1, "constituentBenchmarkSchemeId": "NO_BENCHMARK", "benchmarkRelationships": [], "holdingWeights": [{"level1Code": "195244", "level1Name": "COUNTY OF JACKSON MS 467229AF7", "level2Code": "", "level2Name": "", "level3Code": "", "level3Name": "", "level4Code": "", "level4Name": "", "accountWeight": 0.876764152929679}, {"level1Code": "1800033", "level1Name": "WASHINGTON ST CONVENTION CTR P", "level2Code": "", "level2Name": "", "level3Code": "", "level3Name": "", "level4Code": "", "level4Name": "", "accountWeight": 0.723196476088065}, {"level1Code": "2118748", "level1Name": "KANSAS CITY INDUSTRIAL DEVELOPMENT AUTHORITY 48504NBC2 5 3/1/2046", "level2Code": "", "level2Name": "", "level3Code": "", "level3Name": "", "level4Code": "", "level4Name": "", "accountWeight": 0.720535740429522}, {"level1Code": "2069134", "level1Name": "PEFA INC 70556CAB0 FLT 9/1/2049", "level2Code": "", "level2Name": "", "level3Code": "", "level3Name": "", "level4Code": "", "level4Name": "", "accountWeight": 0.720036471953548}, {"level1Code": "497768", "level1Name": "SALT VERDE FINANCIAL CORP 79575EAS7", "level2Code": "", "level2Name": "", "level3Code": "", "level3Name": "", "level4Code": "", "level4Name": "", "accountWeight": 0.610028267865786}, {"level1Code": "1840685", "level1Name": "COUNTY OF LUCAS OH 549310WE6 5.25 11/15/2048", "level2Code": "", "level2Name": "", "level3Code": "", "level3Name": "", "level4Code": "", "level4Name": "", "accountWeight": 0.575339030224404}, {"level1Code": "1820509", "level1Name": "METROPOLITAN WASHINGTON AIRPORTS AUTHORITY 592647FN6 5 10/1/2043", "level2Code": "", "level2Name": "", "level3Code": "", "level3Name": "", "level4Code": "", "level4Name": "", "accountWeight": 0.571719638205591}, {"level1Code": "2057910", "level1Name": "COMMONWEALTH OF MASSACHUSETTS 57582RWT9 5 5/1/2041", "level2Code": "", "level2Name": "", "level3Code": "", "level3Name": "", "level4Code": "", "level4Name": "", "accountWeight": 0.564334726809143}, {"level1Code": "2154830", "level1Name": "COLORADO HEALTH FACILITIES AUTHORITY 19648FKS2 5 8/1/2044", "level2Code": "", "level2Name": "", "level3Code": "", "level3Name": "", "level4Code": "", "level4Name": "", "accountWeight": 0.562635807515004}, {"level1Code": "1790506", "level1Name": "ALLEGHENY COUNTY HOSPITAL DEVELOPMENT AUTHORITY 01728A4A1", "level2Code": "", "level2Name": "", "level3Code": "", "level3Name": "", "level4Code": "", "level4Name": "", "accountWeight": 0.546972400701315}]}, {"schemeId": "COUNTRY_OF_RISK", "schemeType": "COUNTRY", "levelDepth": 1, "constituentBenchmarkSchemeId": "NO_BENCHMARK", "benchmarkRelationships": [], "holdingWeights": [{"level1Code": "US", "level1Name": "US", "level2Code": "", "level2Name": "", "level3Code": "", "level3Name": "", "level4Code": "", "level4Name": "", "accountWeight": 95.2086005540566}, {"level1Code": "PR", "level1Name": "PR", "level2Code": "", "level2Name": "", "level3Code": "", "level3Name": "", "level4Code": "", "level4Name": "", "accountWeight": 0.918194589032795}, {"level1Code": "VI", "level1Name": "VI", "level2Code": "", "level2Name": "", "level3Code": "", "level3Name": "", "level4Code": "", "level4Name": "", "accountWeight": 0.277878388428759}, {"level1Code": "GU", "level1Name": "GU", "level2Code": "", "level2Name": "", "level3Code": "", "level3Name": "", "level4Code": "", "level4Name": "", "accountWeight": 0.0345946171322252}]}, {"schemeId": "SECTOR_GICS_L1", "schemeType": "SECTOR", "levelDepth": 1, "constituentBenchmarkSchemeId": "NO_BENCHMARK", "benchmarkRelationships": [], "holdingWeights": [{"level1Code": "40", "level1Name": "Financials", "level2Code": "", "level2Name": "", "level3Code": "", "level3Name": "", "level4Code": "", "level4Name": "", "accountWeight": 2.27765841118272}, {"level1Code": "10", "level1Name": "Energy", "level2Code": "", "level2Name": "", "level3Code": "", "level3Name": "", "level4Code": "", "level4Name": "", "accountWeight": 0.134895891294105}]}]}